xlns.py
xlns-1.0.5.dist-info/licenses/LICENSE
xlnsconf/dally.py
xlnsconf/interp_cotran_ufunc.py
xlnsconf/lpvip_ufunc.py
xlnsconf/tab_ufunc.py
xlnsconf/utah_tayco_ufunc.py
xlnsconf/xlnsudFracnorm.py
xlns-1.0.5.dist-info/METADATA
xlns-1.0.5.dist-info/WHEEL
xlns-1.0.5.dist-info/top_level.txt
xlns-1.0.5.dist-info/RECORD
