Metadata-Version: 2.4
Name: xlns
Version: 1.0.5
Summary: A configurable python package for Logarithmic Number System eXperimentation
Author-email: Mark G Arnold <markgarnold@yahoo.com>, Ed Chester <ed.chester@systemlevel.co.uk>
Maintainer-email: Pradeeban Kathiravelu <kk.pradeeban@gmail.com>
Project-URL: Homepage, https://github.com/xlnsresearch/xlns
Project-URL: Issues, https://github.com/xlnsresearch/xlns/issues
Classifier: Programming Language :: Python :: 3
Classifier: License :: OSI Approved :: MIT License
Classifier: Operating System :: OS Independent
Requires-Python: >=3.8
License-File: LICENSE
Dynamic: license-file
